tulipgui/__init__.py
tulipgui/native/QtCore4.dll
tulipgui/native/QtGui4.dll
tulipgui/native/QtNetwork4.dll
tulipgui/native/QtOpenGL4.dll
tulipgui/native/QtWebKit4.dll
tulipgui/native/_tulipgui.pyd
tulipgui/native/glew32.dll
tulipgui/native/libbz2-1.dll
tulipgui/native/libfreetype-6.dll
tulipgui/native/libftgl-tulip-5.2.dll
tulipgui/native/libglib-2.0-0.dll
tulipgui/native/libgraphite2.dll
tulipgui/native/libharfbuzz-0.dll
tulipgui/native/libiconv-2.dll
tulipgui/native/libintl-8.dll
tulipgui/native/libjpeg-8.dll
tulipgui/native/libpcre-1.dll
tulipgui/native/libpng16-16.dll
tulipgui/native/libquazip-tulip-5.2.dll
tulipgui/native/libtess2-tulip-5.2.dll
tulipgui/native/libtulip-gui-5.2.dll
tulipgui/native/libtulip-ogl-5.2.dll
tulipgui/native/plugins/libBillboard-5.2.1.dll
tulipgui/native/plugins/libChristmasTree-5.2.1.dll
tulipgui/native/plugins/libCircle-5.2.1.dll
tulipgui/native/plugins/libCone-5.2.1.dll
tulipgui/native/plugins/libConvolutionClustering-5.2.1.dll
tulipgui/native/plugins/libCross-5.2.1.dll
tulipgui/native/plugins/libCube-5.2.1.dll
tulipgui/native/plugins/libCubeOutlinedTransparent-5.2.1.dll
tulipgui/native/plugins/libCylinder-5.2.1.dll
tulipgui/native/plugins/libDiamond-5.2.1.dll
tulipgui/native/plugins/libFileSystem-5.2.1.dll
tulipgui/native/plugins/libFishEyeInteractor-5.2.1.dll
tulipgui/native/plugins/libFontIcon-5.2.1.dll
tulipgui/native/plugins/libGEXFImport-5.2.1.dll
tulipgui/native/plugins/libGeographicView-5.2.1.dll
tulipgui/native/plugins/libGlowSphere-5.2.1.dll
tulipgui/native/plugins/libHexagone-5.2.1.dll
tulipgui/native/plugins/libHistogramView-5.2.1.dll
tulipgui/native/plugins/libInteractorAddNodeEdge-5.2.1.dll
tulipgui/native/plugins/libInteractorDeleteElement-5.2.1.dll
tulipgui/native/plugins/libInteractorEditEdgeBends-5.2.1.dll
tulipgui/native/plugins/libInteractorGetInformation-5.2.1.dll
tulipgui/native/plugins/libInteractorNavigation-5.2.1.dll
tulipgui/native/plugins/libInteractorRectangleZoom-5.2.1.dll
tulipgui_python-5.2.1.dist-info/METADATA
tulipgui_python-5.2.1.dist-info/WHEEL
tulipgui_python-5.2.1.dist-info/top_level.txt
tulipgui_python-5.2.1.dist-info/RECORD
